happy_python/__init__.py
happy_python/cmd.py
happy_python/datetime.py
happy_python/digest.py
happy_python/domain.py
happy_python/happy_config.py
happy_python/happy_exception.py
happy_python/happy_log.py
happy_python/json.py
happy_python/mail.py
happy_python/misc.py
happy_python/parameter_manager.py
happy_python/resource/tlds.txt
happy_python/str_util.py
happy_python-0.9.0.dist-info/LICENSE
happy_python-0.9.0.dist-info/METADATA
happy_python-0.9.0.dist-info/WHEEL
happy_python-0.9.0.dist-info/RECORD
