Metadata-Version: 2.3
Name: happy-python
Version: 0.9.0
Summary: Happy-Python是一个简单易用的Python库，让编程轻松愉快
License: MIT
Author: Chengdu Geek Camp
Author-email: info@cdgeekcamp.com
Requires-Python: >=3.10.12,<4.0.0
Classifier: Intended Audience :: Developers
Classifier: License :: OSI Approved :: MIT License
Classifier: Operating System :: OS Independent
Classifier: Programming Language :: Python
Classifier: Programming Language :: Python :: 3
Classifier: Programming Language :: Python :: 3.11
Classifier: Programming Language :: Python :: 3.12
Classifier: Programming Language :: Python :: 3.13
Classifier: Topic :: Software Development :: Libraries :: Python Modules
Requires-Dist: pure-eval (>=0.2.3,<0.3.0)
Requires-Dist: varname (>=0.13.5,<0.14.0)
Project-URL: Documentation, https://github.com/geekcampchina/happy-python
Project-URL: Homepage, https://github.com/geekcampchina/happy-python
Project-URL: Repository, https://github.com/geekcampchina/happy-python
